strainpycon_inferencemethods/StrainMatching.py
strainpycon_inferencemethods/__init__.py
strainpycon_inferencemethods/integration.py
strainpycon_inferencemethods/psimplex.py
strainpycon_inferencemethods/recon.py
strainpycon_inferencemethods/utils.py
strainpycon_inferencemethods-1.0.0.dev2.dist-info/METADATA
strainpycon_inferencemethods-1.0.0.dev2.dist-info/WHEEL
strainpycon_inferencemethods-1.0.0.dev2.dist-info/top_level.txt
strainpycon_inferencemethods-1.0.0.dev2.dist-info/RECORD
