Metadata-Version: 2.1
Name: strainpycon-inferencemethods
Version: 1.0.0.dev2
Summary: Strain disambiguation methods for mixed DNA samples. Built upon strainpycon package
Author: Gary Vestal
Author-email: mojihaka@protonmail.com
Classifier: Programming Language :: Python :: 3
Classifier: License :: OSI Approved :: MIT License
Classifier: Operating System :: OS Independent
Provides-Extra: test
Requires-Dist: pytest ; extra == 'test'
Requires-Dist: numpy ; extra == 'test'
Requires-Dist: matplotlib ; extra == 'test'
